README.rst
setup.py
planedict/__init__.py
planedict/planedict.py
planedict.egg-info/PKG-INFO
planedict.egg-info/SOURCES.txt
planedict.egg-info/dependency_links.txt
planedict.egg-info/not-zip-safe
planedict.egg-info/top_level.txt