Metadata-Version: 1.1
Name: planedict
Version: 1.4.0
Summary: PlaneDict is a dict-like class which represents built-in dict class as a 'plane' structure, i.e. pairs path-value. Path is a tuple of keys, value is value which allows in built-in dict.
Home-page: https://github.com/oleg-golovanov/planedict
Author: Oleg Golovanov
Author-email: golovanov.ov@gmail.com
License: MIT
Platform: any
Classifier: Development Status :: 5 - Production/Stable
Classifier: Intended Audience :: Developers
Classifier: License :: OSI Approved :: MIT License
Classifier: Operating System :: OS Independent
Classifier: Programming Language :: Python :: 2.7
Classifier: Programming Language :: Python :: 3.2
Classifier: Programming Language :: Python :: 3.3
Classifier: Programming Language :: Python :: 3.4
Classifier: Programming Language :: Python :: 3.5
Classifier: Programming Language :: Python :: 3.6
Classifier: Programming Language :: Python :: Implementation :: CPython
Classifier: Programming Language :: Python :: Implementation :: PyPy
Classifier: Topic :: Software Development :: Libraries :: Python Modules
